MANIFEST.in
README.md
setup.cfg
setup.py
pocs/__init__.py
pocs/pocs.py
pocs/pocs_dnslog.py
pocs/toolkit.conf
pocs.egg-info/PKG-INFO
pocs.egg-info/SOURCES.txt
pocs.egg-info/dependency_links.txt
pocs.egg-info/entry_points.txt
pocs.egg-info/not-zip-safe
pocs.egg-info/requires.txt
pocs.egg-info/top_level.txt
pocs/data/pass100.txt
pocs/data/pass1000.txt
pocs/data/user-agents.txt
pocs/data/wooyun_domain
pocs/lib/__init__.py
pocs/lib/cli.py
pocs/lib/debug.py
pocs/lib/api/__init__.py
pocs/lib/api/fofa/__init__.py
pocs/lib/api/fofa/pack.py
pocs/lib/api/google/__init__.py
pocs/lib/api/google/pack.py
pocs/lib/api/shodan/__init__.py
pocs/lib/api/shodan/pack.py
pocs/lib/api/zoomeye/__init__.py
pocs/lib/api/zoomeye/base.py
pocs/lib/api/zoomeye/pack.py
pocs/lib/controller/__init__.py
pocs/lib/controller/api.py
pocs/lib/controller/engine.py
pocs/lib/controller/loader.py
pocs/lib/core/__init__.py
pocs/lib/core/common.py
pocs/lib/core/convert.py
pocs/lib/core/data.py
pocs/lib/core/datatype.py
pocs/lib/core/enums.py
pocs/lib/core/exception.py
pocs/lib/core/log.py
pocs/lib/core/option.py
pocs/lib/core/register.py
pocs/lib/core/revision.py
pocs/lib/core/settings.py
pocs/lib/parse/__init__.py
pocs/lib/parse/cmdline.py
pocs/lib/utils/__init__.py
pocs/lib/utils/config.py
pocs/lib/utils/console.py
pocs/lib/utils/update.py
pocs/lib/utils/versioncheck.py
pocs/plugin/__init__.py
pocs/plugin/ceye.py
pocs/plugin/cloudeye.py
pocs/plugin/dnslog.py
pocs/plugin/extracts.py
pocs/plugin/urlparser.py
pocs/plugin/useragent.py
pocs/plugin/util.py
pocs/script/__init__.py
pocs/script/activemq-upload.py
pocs/script/activemq-weakpass.py
pocs/script/brute-example.py
pocs/script/fiyo2.0.7-getshell.py
pocs/script/glassfish-traversal.py
pocs/script/maccms8-rce.py
pocs/script/metinfo-504-sqli.py
pocs/script/navis-webaccess-sqli.py
pocs/script/opensshd-user-enum.py
pocs/script/output.py
pocs/script/phpstudy_backdoor.py
pocs/script/resin-doc-traversal.py
pocs/script/rsync-weakpass.py
pocs/script/samsoftech-admin-bypass.py
pocs/script/shiro-deserial-rce.py
pocs/script/siemens-camera-getpwd.py
pocs/script/spider-example.py
pocs/script/test2.py
pocs/script/vbulletin-ssrf.py
pocs/script/vote-example.py
