Metadata-Version: 1.0
Name: pocs
Version: 1.4
Summary: POC-T Stong Version POC-T加强版
Home-page: https://github.com/jiangsir404/POC-S
Author: rivir
Author-email: rivirsir@163.com
License: UNKNOWN
Keywords: PoC,Exp,POC-T,POC-S,Pentest
Platform: UNKNOWN
